{"latitude":39.74,"longitude":-104.9923,"timezone":"America/Denver","offset":-7,"currently":{"time":1417417200,"summary":"Clear","icon":"clear-night","precipIntensity":0,"precipProbability":0,"temperature":19.49,"apparentTemperature":12.63,"dewPoint":14.45,"humidity":0.8,"windSpeed":4.79,"windBearing":82,"visibility":9.81,"pressure":1033.06},"hourly":{"summary":"Partly cloudy starting in the morning, continuing until evening.","icon":"partly-cloudy-day","data":[{"time":1417417200,"summary":"Clear","icon":"clear-night","precipIntensity":0,"precipProbability":0,"temperature":19.49,"apparentTemperature":12.63,"dewPoint":14.45,"humidity":0.8,"windSpeed":4.79,"windBearing":82,"visibility":9.81,"pressure":1033.06},{"time":1417420800,"summary":"Clear","icon":"clear-night","precipIntensity":0,"precipProbability":0,"temperature":19.33,"apparentTemperature":11.4,"dewPoint":13.63,"humidity":0.78,"windSpeed":5.74,"windBearing":95,"visibility":9.81,"pressure":1032.89},{"time":1417424400,"summary":"Overcast","icon":"cloudy","precipIntensity":0,"precipProbability":0,"temperature":20.1,"apparentTemperature":12.97,"dewPoint":14.94,"humidity":0.8,"windSpeed":5.11,"windBearing":128,"visibility":9.14,"cloudCover":1,"pressure":1032.97},{"time":1417428000,"summary":"Clear","icon":"clear-night","precipIntensity":0,"precipProbability":0,"temperature":20.1,"apparentTemperature":11.06,"dewPoint":15.09,"humidity":0.81,"windSpeed":7.11,"windBearing":137,"visibility":9.14,"pressure":1032.73},{"time":1417431600,"summary":"Clear","icon":"clear-night","precipIntensity":0,"precipProbability":0,"temperature":20.55,"apparentTemperature":11.38,"dewPoint":15.22,"humidity":0.79,"windSpeed":7.38,"windBearing":148,"visibility":9.14,"pressure":1032.12},{"time":1417435200,"summary":"Mostly Cloudy","icon":"partly-cloudy-night","precipIntensity":0,"precipProbability":0,"temperature":21.41,"apparentTemperature":12.76,"dewPoint":16.19,"humidity":0.8,"windSpeed":6.97,"windBearing":142,"visibility":9.81,"cloudCover":0.61,"pressure":1031.38},{"time":1417438800,"summary":"Partly Cloudy","icon":"partly-cloudy-night","precipIntensity":0,"precipProbability":0,"temperature":19.68,"apparentTemperature":8.92,"dewPoint":15.32,"humidity":0.83,"windSpeed":9.29,"windBearing":142,"visibility":10,"cloudCover":0.31,"pressure":1031.16},{"time":1417442400,"summary":"Partly Cloudy","icon":"partly-cloudy-night","precipIntensity":0,"precipProbability":0,"temperature":19.11,"apparentTemperature":11.75,"dewPoint":15.38,"humidity":0.85,"windSpeed":5.17,"windBearing":145,"visibility":10,"cloudCover":0.31,"pressure":1030.86},{"time":1417446000,"summary":"Partly Cloudy","icon":"partly-cloudy-day","precipIntensity":0,"precipProbability":0,"temperature":21.09,"apparentTemperature":21.09,"dewPoint":16.02,"humidity":0.8,"windSpeed":1.69,"windBearing":157,"visibility":10,"cloudCover":0.31,"pressure":1029.72},{"time":1417449600,"summary":"Partly Cloudy","icon":"partly-cloudy-day","precipIntensity":0,"precipProbability":0,"temperature":23.65,"apparentTemperature":19.81,"dewPoint":17.21,"humidity":0.76,"windSpeed":3.04,"windBearing":281,"visibility":10,"cloudCover":0.31,"pressure":1029.5},{"time":1417453200,"summary":"Partly Cloudy","icon":"partly-cloudy-day","precipIntensity":0,"precipProbability":0,"temperature":26.71,"apparentTemperature":21.21,"dewPoint":17.16,"humidity":0.67,"windSpeed":4.66,"windBearing":316,"visibility":10,"cloudCover":0.25,"pressure":1029.14},{"time":1417456800,"summary":"Partly Cloudy","icon":"partly-cloudy-day","precipIntensity":0,"precipProbability":0,"temperature":28.53,"apparentTemperature":22.1,"dewPoint":17.66,"humidity":0.63,"windSpeed":6,"windBearing":310,"visibility":10,"cloudCover":0.25,"pressure":1028.02},{"time":1417460400,"summary":"Partly Cloudy","icon":"partly-cloudy-day","precipIntensity":0,"precipProbability":0,"temperature":30.83,"apparentTemperature":25.25,"dewPoint":17.83,"humidity":0.58,"windSpeed":5.51,"windBearing":310,"visibility":10,"cloudCover":0.25,"pressure":1025.88},{"time":1417464000,"summary":"Partly Cloudy","icon":"partly-cloudy-day","precipIntensity":0,"precipProbability":0,"temperature":33.49,"apparentTemperature":33.49,"dewPoint":18.61,"humidity":0.54,"windSpeed":0,"visibility":10,"cloudCover":0.31,"pressure":1024.4},{"time":1417467600,"summary":"Partly Cloudy","icon":"partly-cloudy-day","precipIntensity":0,"precipProbability":0,"temperature":36.78,"apparentTemperature":36.78,"dewPoint":18.77,"humidity":0.48,"windSpeed":2.74,"windBearing":2,"visibility":10,"cloudCover":0.31,"pressure":1022.77},{"time":1417471200,"summary":"Partly Cloudy","icon":"partly-cloudy-day","precipIntensity":0,"precipProbability":0,"temperature":37.54,"apparentTemperature":35.58,"dewPoint":19.44,"humidity":0.48,"windSpeed":3,"windBearing":350,"visibility":10,"cloudCover":0.31,"pressure":1021.92},{"time":1417474800,"summary":"Partly Cloudy","icon":"partly-cloudy-day","precipIntensity":0,"precipProbability":0,"temperature":37.34,"apparentTemperature":37.34,"dewPoint":19.35,"humidity":0.48,"windSpeed":2.48,"windBearing":49,"visibility":9.81,"cloudCover":0.31,"pressure":1021.81},{"time":1417478400,"summary":"Partly Cloudy","icon":"partly-cloudy-night","precipIntensity":0,"precipProbability":0,"temperature":31.59,"apparentTemperature":31.59,"dewPoint":19.13,"humidity":0.6,"windSpeed":1.87,"windBearing":339,"visibility":9.81,"cloudCover":0.31,"pressure":1022.49},{"time":1417482000,"summary":"Clear","icon":"clear-night","precipIntensity":0,"precipProbability":0,"temperature":29.51,"apparentTemperature":29.51,"dewPoint":19.09,"humidity":0.65,"windSpeed":1.91,"windBearing":215,"visibility":9.57,"cloudCover":0.21,"pressure":1022.76},{"time":1417485600,"summary":"Clear","icon":"clear-night","precipIntensity":0,"precipProbability":0,"temperature":27.41,"apparentTemperature":20.3,"dewPoint":19.05,"humidity":0.7,"windSpeed":6.57,"windBearing":150,"visibility":10,"cloudCover":0.21,"pressure":1023.35},{"time":1417489200,"summary":"Clear","icon":"clear-night","precipIntensity":0,"precipProbability":0,"temperature":26.32,"apparentTemperature":26.32,"dewPoint":18.27,"humidity":0.71,"windSpeed":2.63,"windBearing":118,"visibility":9.34,"cloudCover":0.21,"pressure":1023.39},{"time":1417492800,"summary":"Clear","icon":"clear-night","precipIntensity":0,"precipProbability":0,"temperature":24.9,"apparentTemperature":24.9,"dewPoint":17.95,"humidity":0.74,"windSpeed":2.48,"windBearing":267,"visibility":10,"cloudCover":0.21,"pressure":1022.79},{"time":1417496400,"summary":"Clear","icon":"clear-night","precipIntensity":0,"precipProbability":0,"temperature":26.58,"apparentTemperature":20.63,"dewPoint":18.64,"humidity":0.72,"windSpeed":5.08,"windBearing":189,"visibility":9.34,"cloudCover":0.12,"pressure":1021.58},{"time":1417500000,"summary":"Clear","icon":"clear-night","precipIntensity":0,"precipProbability":0,"temperature":27.04,"apparentTemperature":20.9,"dewPoint":18.74,"humidity":0.7,"windSpeed":5.36,"windBearing":181,"visibility":9.53,"cloudCover":0.12,"pressure":1020.98}]},"daily":{"data":[{"time":1417417200,"summary":"Partly cloudy until evening.","icon":"partly-cloudy-day","sunriseTime":1417442610,"sunsetTime":1417477058,"moonPhase":0.34,"precipIntensity":0,"precipIntensityMax":0,"precipProbability":0,"temperatureMin":19.11,"temperatureMinTime":1417442400,"temperatureMax":37.54,"temperatureMaxTime":1417471200,"apparentTemperatureMin":8.92,"apparentTemperatureMinTime":1417438800,"apparentTemperatureMax":35.58,"apparentTemperatureMaxTime":1417471200,"dewPoint":17.21,"humidity":0.7,"windSpeed":1.65,"windBearing":143,"visibility":9.76,"cloudCover":0.31,"pressure":1026.99}]},"flags":{"sources":["isd"],"isd-stations":["720534-99999","724666-93067","724695-23036","724699-03065","725650-03017"],"units":"us"}}